MANIFEST.in
README.rst
setup.py
spur/__init__.py
spur/errors.py
spur/files.py
spur/io.py
spur/local.py
spur/results.py
spur/tempdir.py
spur.local.egg-info/PKG-INFO
spur.local.egg-info/SOURCES.txt
spur.local.egg-info/dependency_links.txt
spur.local.egg-info/top_level.txt