Metadata-Version: 1.1
Name: spur.local
Version: 0.3.19
Summary: Run commands and manipulate files locally
Home-page: http://github.com/mwilliamson/spur.py
Author: Michael Williamson
Author-email: mike@zwobble.org
License: UNKNOWN
Keywords: shell subprocess process
Platform: UNKNOWN
Classifier: Development Status :: 4 - Beta
Classifier: Intended Audience :: Developers
Classifier: License :: OSI Approved :: BSD License
Classifier: Programming Language :: Python
Classifier: Programming Language :: Python :: 2
Classifier: Programming Language :: Python :: 2.6
Classifier: Programming Language :: Python :: 2.7
Classifier: Programming Language :: Python :: 3
Classifier: Programming Language :: Python :: 3.2
Classifier: Programming Language :: Python :: 3.3
Classifier: Programming Language :: Python :: 3.4
Classifier: Programming Language :: Python :: 3.5
